.gitignore
.readthedocs.yml
.travis.yml
CHANGELOG.rst
LICENSE
MANIFEST.in
README.rst
setup.cfg
setup.py
tox.ini
docs/Makefile
docs/conf.py
docs/index.rst
docs/installation.rst
docs/_static/custom.css
docs/_static/favicon.ico
docs/_static/logo.png
docs/_static/logo_packed.png
docs/_templates/about.html
docs/api/index.rst
docs/usage/standalone.rst
docs/usage/tendril.rst
src/tendril/__init__.py
src/tendril/apiserver/__init__.py
src/tendril/apiserver/routers/__init__.py
src/tendril/apiserver/routers/content.py
src/tendril/apiserver/templates/__init__.py
src/tendril/apiserver/templates/content.py
src/tendril/common/__init__.py
src/tendril/common/content/__init__.py
src/tendril/common/content/exceptions.py
src/tendril/config/__init__.py
src/tendril/config/media.py
src/tendril/db/__init__.py
src/tendril/db/controllers/__init__.py
src/tendril/db/controllers/content.py
src/tendril/db/models/__init__.py
src/tendril/db/models/content.py
src/tendril/db/models/content_formats.py
src/tendril/db/models/content_thumbnails.py
src/tendril/interests/__init__.py
src/tendril/interests/mixins/__init__.py
src/tendril/interests/mixins/content.py
src/tendril/libraries/__init__.py
src/tendril/libraries/mixins/__init__.py
src/tendril/libraries/mixins/content.py
src/tendril/structures/__init__.py
src/tendril/structures/content/__init__.py
src/tendril/structures/content/providers/__init__.py
src/tendril/structures/content/providers/base.py
src/tendril/structures/content/providers/manager.py
src/tendril_structures_media.egg-info/PKG-INFO
src/tendril_structures_media.egg-info/SOURCES.txt
src/tendril_structures_media.egg-info/dependency_links.txt
src/tendril_structures_media.egg-info/requires.txt
src/tendril_structures_media.egg-info/top_level.txt
tests/__init__.py
tests/coveralls.py